{
  "meta": {
    "template_version": "V5.5.12",
    "engine_version": "V3.1",
    "generated_at": "2026-03-30 21:49:21",
    "latest_trade_date": "2026-03-30"
  },
  "portfolio": {
    "initial_capital": 500000.0,
    "cash": 108410.0,
    "market_value": 396000.0,
    "net_value": 504410.0,
    "total_return_pct": 0.882,
    "position_ratio_pct": 79.2,
    "positions": [
      {
        "name": "天津发展",
        "code": "00882",
        "ticker": "0882.HK",
        "shares": 40000,
        "avg_cost": 2.55,
        "close": 2.51,
        "change_pct": -1.1811,
        "market_value": 100400.0,
        "unrealized": -1600.0,
        "sell_trigger": 4.5,
        "weight_pct": 19.9044,
        "status": "实时"
      },
      {
        "name": "京投交通科技",
        "code": "01522",
        "ticker": "1522.HK",
        "shares": 342000,
        "avg_cost": 0.295,
        "close": 0.3,
        "change_pct": 1.6949,
        "market_value": 102600.0,
        "unrealized": 1710.0,
        "sell_trigger": 0.6,
        "weight_pct": 20.3406,
        "status": "实时"
      },
      {
        "name": "华润医药",
        "code": "03320",
        "ticker": "3320.HK",
        "shares": 15000,
        "avg_cost": 5.33,
        "close": 5.7,
        "change_pct": 1.0638,
        "market_value": 85500.0,
        "unrealized": 5550.0,
        "sell_trigger": 9.0,
        "weight_pct": 16.9505,
        "status": "实时"
      },
      {
        "name": "汇贤产业信托",
        "code": "87001",
        "ticker": "87001.HK",
        "shares": 250000,
        "avg_cost": 0.435,
        "close": 0.43,
        "change_pct": -1.1494,
        "market_value": 107500.0,
        "unrealized": -1250.0,
        "sell_trigger": 1.0,
        "weight_pct": 21.312,
        "status": "实时"
      }
    ]
  },
  "today_actions": []
}